{
  "session_id": "20250602_100958",
  "option": "D",
  "option_index": 3,
  "score": 0.0,
  "total_questions": 76,
  "successful_selections": 76,
  "timestamp": "2025-06-02T10:15:34.454385",
  "results": {
    "21": true,
    "24": true,
    "28": true,
    "38": true,
    "45": true,
    "48": true,
    "56": true,
    "58": true,
    "63": true,
    "70": true,
    "71": true,
    "1": false,
    "2": false,
    "3": false,
    "4": false,
    "5": false,
    "6": false,
    "7": false,
    "8": false,
    "9": false,
    "10": false,
    "11": false,
    "12": false,
    "13": false,
    "14": false,
    "15": false,
    "16": false,
    "17": false,
    "18": false,
    "19": false,
    "20": false,
    "22": false,
    "23": false,
    "25": false,
    "26": false,
    "27": false,
    "29": false,
    "30": false,
    "31": false,
    "32": false,
    "33": false,
    "34": false,
    "35": false,
    "36": false,
    "37": false,
    "39": false,
    "40": false,
    "41": false,
    "42": false,
    "43": false,
    "44": false,
    "46": false,
    "47": false,
    "49": false,
    "50": false,
    "51": false,
    "52": false,
    "53": false,
    "54": false,
    "55": false,
    "57": false,
    "59": false,
    "60": false,
    "61": false,
    "62": false,
    "64": false,
    "65": false,
    "66": false,
    "67": false,
    "68": false,
    "69": false,
    "72": false,
    "73": false,
    "74": false,
    "75": false,
    "76": false
  },
  "test_duration_seconds": 48.03342294692993
}