{
  "session_id": "20250602_100958",
  "option": "A",
  "option_index": 0,
  "score": 0.0,
  "total_questions": 76,
  "successful_selections": 76,
  "timestamp": "2025-06-02T10:12:05.347040",
  "results": {
    "3": true,
    "4": true,
    "5": true,
    "6": true,
    "9": true,
    "11": true,
    "15": true,
    "16": true,
    "17": true,
    "19": true,
    "20": true,
    "26": true,
    "27": true,
    "30": true,
    "32": true,
    "33": true,
    "34": true,
    "36": true,
    "37": true,
    "40": true,
    "42": true,
    "44": true,
    "46": true,
    "47": true,
    "49": true,
    "51": true,
    "52": true,
    "53": true,
    "55": true,
    "57": true,
    "60": true,
    "61": true,
    "62": true,
    "64": true,
    "67": true,
    "68": true,
    "69": true,
    "74": true,
    "75": true,
    "1": false,
    "2": false,
    "7": false,
    "8": false,
    "10": false,
    "12": false,
    "13": false,
    "14": false,
    "18": false,
    "21": false,
    "22": false,
    "23": false,
    "24": false,
    "25": false,
    "28": false,
    "29": false,
    "31": false,
    "35": false,
    "38": false,
    "39": false,
    "41": false,
    "43": false,
    "45": false,
    "48": false,
    "50": false,
    "54": false,
    "56": false,
    "58": false,
    "59": false,
    "63": false,
    "65": false,
    "66": false,
    "70": false,
    "71": false,
    "72": false,
    "73": false,
    "76": false
  },
  "test_duration_seconds": 48.29689884185791
}